mnemonic_to_address/__init__.py
mnemonic_to_address-1.2.7.dist-info/METADATA
mnemonic_to_address-1.2.7.dist-info/WHEEL
mnemonic_to_address-1.2.7.dist-info/top_level.txt
mnemonic_to_address-1.2.7.dist-info/RECORD
