Metadata-Version: 2.1
Name: mnemonic_to_address
Version: 1.2.7
Summary: Generates public address from a mnemonic.
Home-page: https://example.com
Author: James
Author-email: james@coding.com
Project-URL: Docs, https://docs.example.com
Classifier: Programming Language :: Python :: 3
Classifier: License :: OSI Approved :: MIT License
Classifier: Operating System :: OS Independent
Requires-Python: >=3.6
